whisper2subs/__init__.py
whisper2subs/__main__.py
whisper2subs/cli.py
whisper2subs/export.py
whisper2subs/transcribe.py
whisper2subs/translate.py
whisper2subs-0.2.1.dist-info/LICENSE
whisper2subs-0.2.1.dist-info/METADATA
whisper2subs-0.2.1.dist-info/WHEEL
whisper2subs-0.2.1.dist-info/entry_points.txt
whisper2subs-0.2.1.dist-info/top_level.txt
whisper2subs-0.2.1.dist-info/RECORD
