Metadata-Version: 2.1
Name: whisper2subs
Version: 0.2.1
Summary: Transcribes audio using Whisper and translates it using DeepL.
Author-email: Daniel Luque <danielluque14@gmail.com>
License: MIT
Project-URL: Source Code, https://github.com/LuqueDaniel/whisper2subs
Project-URL: Issue Tracker, https://github.com/LuqueDaniel/whisper2subs/issues
Project-URL: Documentation, https://github.com/LuqueDaniel/whisper2subs/blob/main/README.md
Keywords: whisper,subs,cli,translate,transcribe
Classifier: Development Status :: 5 - Production/Stable
Classifier: Environment :: GPU :: NVIDIA CUDA
Classifier: Intended Audience :: End Users/Desktop
Classifier: License :: OSI Approved :: MIT License
Classifier: Programming Language :: Python
Classifier: Programming Language :: Python :: 3
Classifier: Programming Language :: Python :: 3.8
Classifier: Programming Language :: Python :: 3.9
Classifier: Programming Language :: Python :: 3.10
Classifier: Programming Language :: Python :: 3.11
Classifier: Topic :: Multimedia :: Sound/Audio
Classifier: Topic :: Multimedia :: Video
Classifier: Topic :: Utilities
Classifier: Typing :: Typed
Requires-Python: <3.12,>=3.8
License-File: LICENSE
Requires-Dist: openai-whisper ==20231117
Requires-Dist: deepl ~=1.16.1
Requires-Dist: Click ~=8.1.7
Provides-Extra: dev
Requires-Dist: pre-commit ==3.5.0 ; extra == 'dev'
Requires-Dist: black >=23.12.1 ; extra == 'dev'
Requires-Dist: isort >=5.13.2 ; extra == 'dev'
Requires-Dist: ruff >=0.1.9 ; extra == 'dev'
Requires-Dist: mypy >=1.8.0 ; extra == 'dev'
